TXMeans/__init__.py
TXMeans/atdc.py
TXMeans/calculate_aggregate_statistics.py
TXMeans/clope.py
TXMeans/coolcat.py
TXMeans/datagenerator.py
TXMeans/datamanager.py
TXMeans/practical.py
TXMeans/rock.py
TXMeans/tkmeans.py
TXMeans/txmeans.py
TXMeans/util.py
TXMeans/validation_measures.py
TXMeans-0.1.1.dist-info/LICENSE
TXMeans-0.1.1.dist-info/METADATA
TXMeans-0.1.1.dist-info/WHEEL
TXMeans-0.1.1.dist-info/top_level.txt
TXMeans-0.1.1.dist-info/RECORD
