Metadata-Version: 2.1
Name: TXMeans
Version: 0.1.1
Summary: parameter-free clustering algorithm
Author: Riccardo Guidotti, Anna Monreale, Mirco Nanni, Fosca Giannotti, Dino Pedreschi
License: GPL
Classifier: Programming Language :: Python :: 3
Classifier: License :: OSI Approved :: GNU General Public License v3 (GPLv3)
Classifier: Operating System :: OS Independent
Requires-Python: >=3
License-File: LICENSE
